[{
    "event": "Pet Expo Thailand 2024",
    "name": "Thai Love Animal Foundation",
    "date": "18 Aug 2024",
    "uri": "https://th.bing.com/th/id/OIP.LnqpjDGNi0qnO2WmrNbi2wAAAA?rs=1&pid=ImgDetMain"
},
{
    "event": "Pet Expo Thailand 2024",
    "name": "Adopt me Please",
    "date": "19 Aug 2024",
    "uri": "https://th.bing.com/th/id/OIP.LnqpjDGNi0qnO2WmrNbi2wAAAA?rs=1&pid=ImgDetMain"
},
{
    "event": "Pet Expo Thailand 2024",
    "name": "Hua-Hin Pos Sheiter",
    "date": "19 Aug 2024",
    "uri": "https://th.bing.com/th/id/OIP.LnqpjDGNi0qnO2WmrNbi2wAAAA?rs=1&pid=ImgDetMain"
}]
